LICENSE
MANIFEST.in
README
setup.cfg
setup.py
tgext/__init__.py
tgext.menu.egg-info/PKG-INFO
tgext.menu.egg-info/SOURCES.txt
tgext.menu.egg-info/dependency_links.txt
tgext.menu.egg-info/namespace_packages.txt
tgext.menu.egg-info/paster_plugins.txt
tgext.menu.egg-info/requires.txt
tgext.menu.egg-info/top_level.txt
tgext/menu/__init__.py
tgext/menu/caches.py
tgext/menu/decorators.py
tgext/menu/functions.py
tgext/menu/util.py
tgext/menu/templates/__init__.py
tgext/menu/templates/divmenu.mak