Metadata-Version: 1.0
Name: tgext.menu
Version: 0.6
Summary: Automatic menu/navbar/sidebar generation extension for TurboGears
Home-page: http://bitbucket.org/pedersen/tgext.menu
Author: Michael Pedersen
Author-email: m.pedersen@icelus.org
License: UNKNOWN
Platform: UNKNOWN
